causarray/DR_estimation.py
causarray/DR_inference.py
causarray/DR_learner.py
causarray/__about__.py
causarray/__init__.py
causarray/gcate.py
causarray/gcate_glm.py
causarray/gcate_likelihood.py
causarray/gcate_opt.py
causarray/utils.py
causarray-0.0.5.dist-info/METADATA
causarray-0.0.5.dist-info/WHEEL
causarray-0.0.5.dist-info/licenses/LICENSE
causarray-0.0.5.dist-info/RECORD
