Metadata-Version: 2.4
Name: causarray
Version: 0.0.5
Summary: causarray is a Python module for simultaneous causal inference with an array of outcomes.
Author-email: Jin-Hong Du <jinhongd@andrew.cmu.com>, Maya Shen <myshen@andrew.cmu.edu>, Hansruedi Mathys <mathysh@pitt.edu>, Kathryn Roeder <jinhongd@andrew.cmu.com>
Maintainer-email: Jin-Hong Du <jinhongd@andrew.cmu.com>
License: MIT License
License-File: LICENSE
Classifier: Intended Audience :: Developers
Classifier: License :: OSI Approved :: MIT License
Classifier: Programming Language :: Python :: 3
Requires-Python: >=3.8
Requires-Dist: joblib
Requires-Dist: matplotlib
Requires-Dist: numba
Requires-Dist: numpy
Requires-Dist: pandas
Requires-Dist: pip
Requires-Dist: scikit-learn
Requires-Dist: scipy
Requires-Dist: sklearn-ensemble-cv
Requires-Dist: statsmodels
Requires-Dist: tqdm
